fritzToInfluxHA/__init__.py
fritzToInfluxHA/fritzResponse.py
fritzToInfluxHA/fritzToInfluxHA.py
fritzToInfluxHA/fritz/FritzBox.py
fritzToInfluxHA/fritz/FritzHaDevice.py
fritzToInfluxHA/fritz/__init__.py
fritzToInfluxHA/influx/__init__.py
fritzToInfluxHA-1.0.0.dist-info/LICENSE
fritzToInfluxHA-1.0.0.dist-info/METADATA
fritzToInfluxHA-1.0.0.dist-info/WHEEL
fritzToInfluxHA-1.0.0.dist-info/top_level.txt
fritzToInfluxHA-1.0.0.dist-info/RECORD
