Metadata-Version: 2.1
Name: fritzToInfluxHA
Version: 1.0.0
Summary: Periodially read Fritz!Box HA device data and store in InfluxDB
Home-page: https://github.com/signag/fritzToInfluxHA
Author: signag
Author-email: siegfried.nagel@t-online.de
Project-URL: Source, https://github.com/signag/fritzToInfluxHA/
Keywords: RaspberryPi Fritz!Box HomeAutomation Monitoring InfluxDB
Classifier: Development Status :: 3 - Alpha
Classifier: Intended Audience :: Developers
Classifier: Topic :: Software Development :: Build Tools
Classifier: License :: OSI Approved :: MIT License
Classifier: Programming Language :: Python :: 3
Requires-Python: >=3.5
License-File: LICENSE
Requires-Dist: influxdb-client (==1.32.0)
Requires-Dist: logging-plus (==1.0.0)
Requires-Dist: requests (==2.28.1)
Requires-Dist: python-dateutil (==2.8.2) ; python_version >= "2.7" and python_version not in "3.0, 3.1, 3.2, 3.3"
Requires-Dist: six (==1.16.0) ; python_version >= "2.7" and python_version not in "3.0, 3.1, 3.2, 3.3"
Requires-Dist: urllib3 (==1.26.12) ; python_version >= "2.7" and python_version not in "3.0, 3.1, 3.2, 3.3, 3.4, 3.5" and python_version < "4.0"
Requires-Dist: idna (==3.4) ; python_version >= "3.5"
Requires-Dist: certifi (==2022.9.24) ; python_version >= "3.6"
Requires-Dist: charset-normalizer (==2.1.1) ; python_version >= "3.6"
Requires-Dist: typing-extensions (==4.3.0) ; python_version >= "3.7"
Requires-Dist: reactivex (==4.0.4) ; python_version >= "3.7" and python_version < "4.0"
Provides-Extra: dev
